odoo/addons/auth_oidc_environment/README.rst
odoo/addons/auth_oidc_environment/__init__.py
odoo/addons/auth_oidc_environment/__manifest__.py
odoo/addons/auth_oidc_environment/i18n/auth_oidc_environment.pot
odoo/addons/auth_oidc_environment/i18n/it.po
odoo/addons/auth_oidc_environment/models/__init__.py
odoo/addons/auth_oidc_environment/models/auth_oauth_provider.py
odoo/addons/auth_oidc_environment/readme/CONFIGURE.md
odoo/addons/auth_oidc_environment/readme/CONTRIBUTORS.md
odoo/addons/auth_oidc_environment/readme/DESCRIPTION.md
odoo/addons/auth_oidc_environment/readme/USAGE.md
odoo/addons/auth_oidc_environment/static/description/icon.png
odoo/addons/auth_oidc_environment/static/description/index.html
odoo/addons/auth_oidc_environment/tests/__init__.py
odoo/addons/auth_oidc_environment/tests/test_auth_oidc_environment.py
odoo_addon_auth_oidc_environment-18.0.1.0.0.3.dist-info/METADATA
odoo_addon_auth_oidc_environment-18.0.1.0.0.3.dist-info/WHEEL
odoo_addon_auth_oidc_environment-18.0.1.0.0.3.dist-info/top_level.txt
odoo_addon_auth_oidc_environment-18.0.1.0.0.3.dist-info/RECORD
